vaultx/__init__.py
vaultx/_types.py
vaultx/adapters.py
vaultx/api/__init__.py
vaultx/api/async_auth_methods/__init__.py
vaultx/api/async_auth_methods/approle.py
vaultx/api/async_auth_methods/aws.py
vaultx/api/async_auth_methods/azure.py
vaultx/api/async_auth_methods/cert.py
vaultx/api/async_auth_methods/gcp.py
vaultx/api/async_auth_methods/github.py
vaultx/api/async_auth_methods/jwt.py
vaultx/api/async_auth_methods/kubernetes.py
vaultx/api/async_auth_methods/ldap.py
vaultx/api/async_auth_methods/legacy_mfa.py
vaultx/api/async_auth_methods/oidc.py
vaultx/api/async_auth_methods/okta.py
vaultx/api/async_auth_methods/radius.py
vaultx/api/async_auth_methods/token.py
vaultx/api/async_auth_methods/userpass.py
vaultx/api/async_secrets_engines/__init__.py
vaultx/api/async_secrets_engines/active_directory.py
vaultx/api/async_secrets_engines/aws.py
vaultx/api/async_secrets_engines/azure.py
vaultx/api/async_secrets_engines/consul.py
vaultx/api/async_secrets_engines/database.py
vaultx/api/async_secrets_engines/gcp.py
vaultx/api/async_secrets_engines/identity.py
vaultx/api/async_secrets_engines/kv.py
vaultx/api/async_secrets_engines/kv_v1.py
vaultx/api/async_secrets_engines/kv_v2.py
vaultx/api/async_secrets_engines/ldap.py
vaultx/api/async_secrets_engines/pki.py
vaultx/api/async_secrets_engines/rabbitmq.py
vaultx/api/async_secrets_engines/ssh.py
vaultx/api/async_secrets_engines/transform.py
vaultx/api/async_secrets_engines/transit.py
vaultx/api/async_system_backend/__init__.py
vaultx/api/async_system_backend/audit.py
vaultx/api/async_system_backend/auth.py
vaultx/api/async_system_backend/capabilities.py
vaultx/api/async_system_backend/health.py
vaultx/api/async_system_backend/init.py
vaultx/api/async_system_backend/key.py
vaultx/api/async_system_backend/leader.py
vaultx/api/async_system_backend/lease.py
vaultx/api/async_system_backend/mount.py
vaultx/api/async_system_backend/namespace.py
vaultx/api/async_system_backend/policies.py
vaultx/api/async_system_backend/policy.py
vaultx-0.0.5.dist-info/LICENSE.txt
vaultx-0.0.5.dist-info/METADATA
vaultx-0.0.5.dist-info/WHEEL
vaultx-0.0.5.dist-info/RECORD
