Metadata-Version: 2.3
Name: vaultx
Version: 0.0.5
Summary: Python 3.x httpx client for HashiCorp's Vault
License: Apache-2.0
Author: klukashka
Author-email: klukin0202@yandex.ru
Requires-Python: >=3.9,<4.0
Classifier: License :: OSI Approved :: Apache Software License
Classifier: Programming Language :: Python :: 3
Classifier: Programming Language :: Python :: 3.9
Classifier: Programming Language :: Python :: 3.10
Classifier: Programming Language :: Python :: 3.11
Classifier: Programming Language :: Python :: 3.12
Classifier: Programming Language :: Python :: 3.13
Provides-Extra: parser
Requires-Dist: aiohttp (>=3.11.13,<4.0.0)
Requires-Dist: httpx (>=0.28.1,<0.29.0)
Requires-Dist: pyhcl (>=0.4.4,<0.5.0) ; extra == "parser"
